xm_slurm/__init__.py
xm_slurm/batching.py
xm_slurm/config.py
xm_slurm/console.py
xm_slurm/constants.py
xm_slurm/dependencies.py
xm_slurm/executables.py
xm_slurm/execution.py
xm_slurm/executors.py
xm_slurm/experiment.py
xm_slurm/filesystems.py
xm_slurm/job_blocks.py
xm_slurm/metadata_context.py
xm_slurm/packageables.py
xm_slurm/resources.py
xm_slurm/status.py
xm_slurm/types.py
xm_slurm/utils.py
xm_slurm/api/__init__.py
xm_slurm/api/abc.py
xm_slurm/api/models.py
xm_slurm/api/sqlite/client.py
xm_slurm/api/web/client.py
xm_slurm/contrib/__init__.py
xm_slurm/contrib/clusters/__init__.py
xm_slurm/contrib/clusters/drac.py
xm_slurm/experimental/parameter_controller.py
xm_slurm/packaging/__init__.py
xm_slurm/packaging/docker.py
xm_slurm/packaging/registry.py
xm_slurm/packaging/router.py
xm_slurm/packaging/utils.py
xm_slurm/scripts/_cloudpickle.py
xm_slurm/scripts/cli.py
xm_slurm/templates/docker/docker-bake.hcl.j2
xm_slurm/templates/docker/mamba.Dockerfile
xm_slurm/templates/docker/python.Dockerfile
xm_slurm/templates/docker/uv.Dockerfile
xm_slurm/templates/slurm/entrypoint.bash.j2
xm_slurm/templates/slurm/job-array.bash.j2
xm_slurm/templates/slurm/job-group.bash.j2
xm_slurm/templates/slurm/job.bash.j2
xm_slurm/templates/slurm/fragments/monitor.bash.j2
xm_slurm/templates/slurm/fragments/proxy.bash.j2
xm_slurm/templates/slurm/library/retry.bash
xm_slurm/templates/slurm/runtimes/apptainer.bash.j2
xm_slurm/templates/slurm/runtimes/podman.bash.j2
xmanager_slurm-0.4.21.dist-info/METADATA
xmanager_slurm-0.4.21.dist-info/WHEEL
xmanager_slurm-0.4.21.dist-info/entry_points.txt
xmanager_slurm-0.4.21.dist-info/licenses/LICENSE.md
xmanager_slurm-0.4.21.dist-info/RECORD
