Metadata-Version: 2.4
Name: xmanager-slurm
Version: 0.4.21
Summary: Slurm backend for XManager.
Project-URL: GitHub, https://github.com/jessefarebro/xm-slurm
Author-email: Jesse Farebrother <jfarebro@cs.mcgill.ca>
License: MIT
License-File: LICENSE.md
Classifier: License :: OSI Approved :: Apache Software License
Classifier: License :: OSI Approved :: MIT License
Classifier: Operating System :: OS Independent
Classifier: Programming Language :: Python :: 3
Classifier: Programming Language :: Python :: 3.10
Classifier: Programming Language :: Python :: 3.11
Classifier: Programming Language :: Python :: 3.12
Requires-Python: >=3.10
Requires-Dist: aiofile>=3.9.0
Requires-Dist: asyncssh>=2.19.0
Requires-Dist: backoff>=2.2.1
Requires-Dist: cloudpickle>=3.0.0
Requires-Dist: httpx>=0.28.1
Requires-Dist: humanize>=4.8.0
Requires-Dist: jinja2>=3.1.2
Requires-Dist: more-itertools>=10.2.0
Requires-Dist: rich>=13.5.2
Requires-Dist: toml>=0.10.2
Requires-Dist: wrapt>=1.16.0
Requires-Dist: xmanager>=0.5.0
